squeezebox_controller/__init__.py
squeezebox_controller/string_distance.py
squeezebox_controller-1.0.4.dist-info/LICENSE.txt
squeezebox_controller-1.0.4.dist-info/METADATA
squeezebox_controller-1.0.4.dist-info/WHEEL
squeezebox_controller-1.0.4.dist-info/top_level.txt
squeezebox_controller-1.0.4.dist-info/RECORD
