Metadata-Version: 2.1
Name: squeezebox-controller
Version: 1.0.4
Summary: A python api for controlling logitech squeezeboxes via the squeezebox server.
Home-page: https://github.com/jackoson/squeezebox-controller
Author: Jackoson
License: UNKNOWN
Platform: UNKNOWN
Classifier: Programming Language :: Python :: 3
Classifier: License :: OSI Approved :: MIT License
Classifier: Operating System :: OS Independent
Requires-Dist: requests
Requires-Dist: pylev
